README.md
setup.cfg
setup.py
choice_sort_pack/__init__.py
choice_sort_pack/__main__.py
choice_sort_pack/choice_sort.py
choice_sort_pack/input_check.py
choice_sort_pack.egg-info/PKG-INFO
choice_sort_pack.egg-info/SOURCES.txt
choice_sort_pack.egg-info/dependency_links.txt
choice_sort_pack.egg-info/requires.txt
choice_sort_pack.egg-info/top_level.txt