Metadata-Version: 2.1
Name: choice-sort-pack
Version: 1.1
Summary: Модуль, проводящий сортировку выбором
License: MIT
